MANIFEST.in
README.rst
requirements.txt
setup.cfg
setup.py
dbcron/__init__.py
dbcron/admin.py
dbcron/apps.py
dbcron/calendar.py
dbcron/consumers.py
dbcron/forms.py
dbcron/models.py
dbcron/querysets.py
dbcron/settings.py
dbcron/signals.py
dbcron/tests.py
dbcron/utils.py
dbcron/validators.py
dbcron/views.py
dbcron/contrib/__init__.py
dbcron/contrib/filtersets.py
dbcron/contrib/tables.py
dbcron/management/__init__.py
dbcron/management/commands/__init__.py
dbcron/management/commands/_base.py
dbcron/management/commands/crond.py
dbcron/management/commands/run_jobs.py
dbcron/migrations/0001_initial.py
dbcron/migrations/__init__.py
dbcron/tests/__init__.py
dbcron/tests/factories.py
dbcron/tests/test_calendar.py
dbcron/tests/test_commands.py
dbcron/tests/test_validators.py
django_dbcron.egg-info/PKG-INFO
django_dbcron.egg-info/SOURCES.txt
django_dbcron.egg-info/dependency_links.txt
django_dbcron.egg-info/requires.txt
django_dbcron.egg-info/top_level.txt