Metadata-Version: 1.1
Name: django-dbcron
Version: 0.5.3
Summary: Manage your crontab directly from DB.
Home-page: https://github.com/cloudspectatordevelopment/django-dbcron
Author: Anthony Monthe (ZuluPro)
Author-email: amonthe@cloudspectator.com
License: BSD
Keywords: django,cron,crontab
Platform: UNKNOWN
Classifier: Development Status :: 4 - Beta
Classifier: Environment :: Web Environment
Classifier: Environment :: Console
Classifier: Framework :: Django
Classifier: Intended Audience :: Developers
Classifier: License :: OSI Approved :: BSD License
Classifier: Natural Language :: English
Classifier: Operating System :: OS Independent
Classifier: Programming Language :: Python
Classifier: Programming Language :: Python :: 2
Classifier: Programming Language :: Python :: 2.7
Classifier: Programming Language :: Python :: 3
Classifier: Programming Language :: Python :: 3.3
Classifier: Programming Language :: Python :: 3.4
Classifier: Programming Language :: Python :: 3.5
